{
    "name": "fanSpeedMode_setValue",
    "description": "This function is used to set the fan speed mode of a SmartThings device.",
    "parameters": [
        {
            "name": "location",
            "type": "string",
            "description": "The location where the device is located.",
            "optional": true
        },
        {
            "name": "room",
            "type": "string",
            "description": "The room where the device is located.",
            "optional": true
        },
        {
            "name": "device",
            "type": "string",
            "description": "The name or type of the device to set the fan speed mode.",
            "optional": true
        },
        {
            "name": "predefinedFanSpeedMode",
            "type": "string",
            "description": "The predefined fan speed mode to set for the device.",
            "optional": true
        }
    ],
    "depends_upon": [],
    "output": []
}